maitag/analysis.py
maitag/anonymize.py
maitag/constants.py
maitag/fake_identities.py
maitag/low_recall_tagger.hist.py
maitag/sklearn_multilabel_demo.py
maitag/spacy_language_model.py
maitag/tagging_models.py
maitag-0.0.1.dist-info/WHEEL
maitag-0.0.1.dist-info/METADATA
maitag-0.0.1.dist-info/RECORD
