Metadata-Version: 2.1
Name: maitag
Version: 0.0.1
Summary: MAIT - Machine-Assisted Intent Tagging
License: MIT
Author: Hobson Lane
Author-email: hobson@tangibleai.com
Requires-Python: >=3.9,<4.0
Classifier: License :: OSI Approved :: MIT License
Classifier: Programming Language :: Python :: 3
Classifier: Programming Language :: Python :: 3.10
Classifier: Programming Language :: Python :: 3.9
Requires-Dist: Django (>=4.0.6,<5.0.0)
Requires-Dist: fng-api (>=0.0.5,<0.0.6)
Requires-Dist: huggingface-hub (>=0.8.1,<0.9.0)
Requires-Dist: jupyter (>=1.0.0,<2.0.0)
Requires-Dist: pandas (>=1.4.3,<2.0.0)
Requires-Dist: scikit-learn (>=1.1.1,<2.0.0)
Requires-Dist: seaborn (>=0.11.2,<0.12.0)
Requires-Dist: sentence-transformers (>=2.2.2,<3.0.0)
Requires-Dist: simpletransformers (>=0.63.7,<0.64.0)
Requires-Dist: spacy (>=3.4.0,<4.0.0)
Requires-Dist: torch (>=1.12.0,<2.0.0)
Requires-Dist: transformers (>=4.20.1,<5.0.0)
